MIOFlow/__init__.py
MIOFlow/constants.py
MIOFlow/datasets.py
MIOFlow/eval.py
MIOFlow/exp.py
MIOFlow/geo.py
MIOFlow/losses.py
MIOFlow/mioflow.py
MIOFlow/models.py
MIOFlow/ode.py
MIOFlow/phate_autoencoder.py
MIOFlow/phate_decoder.py
MIOFlow/plots.py
MIOFlow/train.py
MIOFlow/utils.py
mioflow-0.1.9.dist-info/licenses/LICENSE.md
mioflow-0.1.9.dist-info/METADATA
mioflow-0.1.9.dist-info/WHEEL
mioflow-0.1.9.dist-info/top_level.txt
mioflow-0.1.9.dist-info/RECORD
