Metadata-Version: 2.4
Name: MIOFlow
Version: 0.1.9
Summary: MIOFlow is a Python package for modeling and analyzing single-cell RNA-seq data using optimal flows.
Author-email: xingzhis <xingzhi.sun@yale.edu>, bjoaofelipe <joaofelipe.rocha@yale.edu>
Keywords: neural ode,trajectory,emd,Optimal Transport,single cell RNA,mioflow
Classifier: Development Status :: 2 - Pre-Alpha
Classifier: Intended Audience :: Developers
Classifier: Programming Language :: Python :: 3
Classifier: Programming Language :: Python :: 3 :: Only
Requires-Python: >=3.8
License-File: LICENSE.md
Requires-Dist: numpy<=1.26.4
Requires-Dist: pandas
Requires-Dist: torch>=1.11.0
Requires-Dist: pytorch-lightning
Requires-Dist: hydra-core
Requires-Dist: omegaconf
Requires-Dist: torchsde
Requires-Dist: torchdiffeq
Requires-Dist: scikit-learn
Requires-Dist: scipy
Requires-Dist: matplotlib
Requires-Dist: seaborn
Requires-Dist: phate
Requires-Dist: graphtools
Requires-Dist: pot
Requires-Dist: tqdm
Requires-Dist: pyyaml
Requires-Dist: scanpy>=1.9.8
Requires-Dist: ipywidgets>=8.1.7
Requires-Dist: ipykernel>=6.29.5
Requires-Dist: notebook>=7.3.3
Dynamic: license-file
